MANIFEST.in
README.md
setup.py
afanimation/__init__.py
afanimation/afanimation.py
afanimation/afapatterns.py
afanimation.egg-info/PKG-INFO
afanimation.egg-info/SOURCES.txt
afanimation.egg-info/dependency_links.txt
afanimation.egg-info/requires.txt
afanimation.egg-info/top_level.txt
afanimation.egg-info/zip-safe